cs2_nav-0.3.17.dist-info/METADATA
cs2_nav-0.3.17.dist-info/WHEEL
cs2_nav-0.3.17.dist-info/licenses/LICENSE
cs2_nav.libs/libgcc_s-b5472b99.so.1
cs2_nav/__init__.py
cs2_nav/__init__.pyi
cs2_nav/py.typed
cs2_nav/cs2_nav.pypy39-pp73-x86-linux-gnu.so
cs2_nav-0.3.17.dist-info/RECORD
