Metadata-Version: 2.4
Name: cs2_nav
Version: 0.3.17
Classifier: Programming Language :: Rust
Classifier: Programming Language :: Python :: Implementation :: CPython
Classifier: Programming Language :: Python :: Implementation :: PyPy
License-File: LICENSE
Summary: Package to produce CS2 meeting point plots.
Keywords: CS2,visualization
Author: Jan-Eric <janericnitschke@gmail.com
Author-email: Jan-Eric <janericnitschke@gmail.com
License: MIT
Requires-Python: >=3.8
Project-URL: Source Code, https://github.com/JanEricNitschke/cs2_meeting_points
